[{
  "_id": {
    "$oid": "6632c03e3acb9a274773ec06"
  },
  "name": "HTML",
  "date": "2023-10-07",
  "task_id": {
    "$oid": "6632c0a43acb9a274773ec0c"
  }
},
{
  "_id": {
    "$oid": "6632c03e3acb9a274773ec07"
  },
  "name": "CSS",
  "date": "2023-10-18"
},
{
  "_id": {
    "$oid": "6632c03e3acb9a274773ec08"
  },
  "name": "JS",
  "date": "2023-10-24",
  "task_id": {
    "$oid": "6632c0a43acb9a274773ec0e"
  }
},
{
  "_id": {
    "$oid": "6632c03e3acb9a274773ec09"
  },
  "name": "React JS",
  "date": "2023-11-28",
  "task_id": {
    "$oid": "6632c0a43acb9a274773ec0f"
  }
},
{
  "_id": {
    "$oid": "6632c03e3acb9a274773ec0a"
  },
  "name": "Node JS",
  "date": "2023-11-29"
}]